pyinvc/__init__.py
pyinvc/billing.py
pyinvc-0.1.37.dist-info/LICENSE
pyinvc-0.1.37.dist-info/METADATA
pyinvc-0.1.37.dist-info/WHEEL
pyinvc-0.1.37.dist-info/RECORD
