Metadata-Version: 2.3
Name: pyinvc
Version: 0.1.37
Summary: 
Author: Alireza
Author-email: arg274@gmail.com
Requires-Python: >=3.12,<4.0
Classifier: Programming Language :: Python :: 3
Classifier: Programming Language :: Python :: 3.12
Classifier: Programming Language :: Python :: 3.13
Requires-Dist: httpx (>=0.28.1,<0.29.0)
Requires-Dist: python-decouple (>=3.8,<4.0)
